WebCrawler/WebCrawler.py
OSS_Webcrawler-0.0.1.dist-info/METADATA
OSS_Webcrawler-0.0.1.dist-info/WHEEL
OSS_Webcrawler-0.0.1.dist-info/top_level.txt
OSS_Webcrawler-0.0.1.dist-info/RECORD
